Metadata-Version: 2.1
Name: pybowie
Version: 1.0.5
Summary: Bayesian optimization for constrained or unconstrained, continuous, discrete or mixed data problems
Home-page: https://github.com/JavierMorlet/pyBOWIE
Author: Javier Morlet-Espinosa, Antonio Flores-Tlacuahuac
Author-email: a00833961@tec.mx
License-File: LICENSE.txt
Requires-Dist: numpy>=1.23.5
Requires-Dist: sympy>=1.11.1
Requires-Dist: pandas>=2.0.3
Requires-Dist: GPy>=1.10.0
Requires-Dist: gpflow>=2.9.2
Requires-Dist: scipy>=1.10.1
Requires-Dist: scikit-learn>=1.1.3
Requires-Dist: properscoring>=0.1
Requires-Dist: prince>=0.12.1
Requires-Dist: multiprocess>=0.70.16
Requires-Dist: matplotlib>=3.7.3
